mcp_pdb/__init__.py
mcp_pdb/main.py
mcp_pdb-0.4.0.dist-info/METADATA
mcp_pdb-0.4.0.dist-info/WHEEL
mcp_pdb-0.4.0.dist-info/entry_points.txt
mcp_pdb-0.4.0.dist-info/RECORD
