Metadata-Version: 2.4
Name: mcp-pdb
Version: 0.4.0
Summary: MCP to use the python debugger, inspired by debug-gym
Author-email: samefarrar <67292186+samefarrar@users.noreply.github.com>
License: MIT
Classifier: License :: OSI Approved :: MIT License
Classifier: Operating System :: OS Independent
Classifier: Programming Language :: Python :: 3
Requires-Python: >=3.13
Requires-Dist: mcp[cli]>=1.6.0
